zoom_api/__init__.py
zoom_api/config.py
zoom_api/init.py
zoom_api/logging_config.py
zoom_api/message_formatter.py
zoom_api/zoom_api.py
zoom_api/zoom_client.py
codef2_zoom_notifier-0.1.0.dist-info/METADATA
codef2_zoom_notifier-0.1.0.dist-info/WHEEL
codef2_zoom_notifier-0.1.0.dist-info/entry_points.txt
codef2_zoom_notifier-0.1.0.dist-info/top_level.txt
codef2_zoom_notifier-0.1.0.dist-info/RECORD
