Metadata-Version: 2.1
Name: codef2-zoom-notifier
Version: 0.1.0
Summary: A package for sending Zoom messages.
Home-page: https://github.com/yourusername/my_zoom_package
Author: Muthasir
Author-email: muthasir@aggregateintelligence.in
License: UNKNOWN
Platform: UNKNOWN
Classifier: Programming Language :: Python :: 3
Classifier: License :: OSI Approved :: MIT License
Classifier: Operating System :: OS Independent
Requires-Python: >=3.6
Requires-Dist: requests
